ImageToASCII/__init__.py
ImageToASCII/__main__.py
ImageToASCII/ascii_converter.py
ImageToASCII/utils.py
ImageToASCII/ui/__init__.py
ImageToASCII/ui/app.py
ImageToASCII/ui/char_selector.py
ImageToASCII/ui/export_top.py
ImageToASCII/ui/file_selector.py
ImageToASCII/ui/result_viewer.py
ImageToASCII/ui/size_selector.py
ImageToASCII/ui/status_bar.py
slavlasagnas_image_to_ascii-0.1.0.dist-info/licenses/LICENSE
slavlasagnas_image_to_ascii-0.1.0.dist-info/METADATA
slavlasagnas_image_to_ascii-0.1.0.dist-info/WHEEL
slavlasagnas_image_to_ascii-0.1.0.dist-info/entry_points.txt
slavlasagnas_image_to_ascii-0.1.0.dist-info/top_level.txt
slavlasagnas_image_to_ascii-0.1.0.dist-info/RECORD
