Metadata-Version: 2.4
Name: slavlasagnas-image-to-ascii
Version: 0.1.0
Summary: A Tkinter-based Image to ASCII Art converter
Author-email: SlavLasagna <martinguionniere@gmail.com>
License:                     GNU GENERAL PUBLIC LICENSE
Project-URL: Homepage, https://github.com/SlavLasagna/IToA
License-File: LICENSE
Requires-Dist: pillow
Dynamic: license-file
